fake_elasticsearch/__init__.py
fake_elasticsearch/cli.py
fake_elasticsearch-2.0.2.dist-info/METADATA
fake_elasticsearch-2.0.2.dist-info/WHEEL
fake_elasticsearch-2.0.2.dist-info/top_level.txt
fake_elasticsearch-2.0.2.dist-info/RECORD
