Metadata-Version: 2.1
Name: fake-elasticsearch
Version: 2.0.2
Summary: Fake elasticsearch python client.
Home-page: UNKNOWN
Author: fatelei
Author-email: fatelei@gmail.com
License: BSD License
Platform: UNKNOWN
Classifier: Development Status :: 5 - Production/Stable
Classifier: Environment :: Console
Classifier: Environment :: Web Environment
Classifier: Intended Audience :: Developers
Classifier: License :: OSI Approved :: BSD License
Classifier: Programming Language :: Python :: 2.7
Classifier: Topic :: Software Development :: Libraries
Classifier: Topic :: System :: Logging
Requires-Dist: elasticsearch
